{
	"code": 0,
	"subcode": 0,
	"message": "",
	"default": 0,
	"data": {
		"total": 1814,
		"auditNum": 0,
		"auditON": true,
		"authorInfo": {
			"msg": "",
			"htmlMsg": "",
			"sign": ""
		},
		"commentList": [
			{
				"id": "2000060229",
				"secret": 0,
				"pasterid": "",
				"bmp": "885195800202e101",
				"pubtime": "2014-06-11 00:15:39",
				"modifytime": 0,
				"effect": 4194304,
				"type": 0,
				"uin": 1991789548,
				"nickname": "蛹子小姐",
				"capacity": 5939,
				"htmlContent": "我还不困啊\u003Cimg src=\u0022\/qzone\/em\/e328552.gif\u0022  \/>\u003Cwbr  \/>",
				"ubbContent": "我还不困啊[em]e328552[\/em]",
				"signature": "",
				"replyList": []
			},
			{
				"id": "2000060228",
				"secret": 0,
				"pasterid": "",
				"bmp": "885195800202e101",
				"pubtime": "2014-06-10 11:06:59",
				"modifytime": 0,
				"effect": 4194304,
				"type": 0,
				"uin": 1991789548,
				"nickname": "蛹子小姐",
				"capacity": 5959,
				"htmlContent": "蹭一蹭",
				"ubbContent": "蹭一蹭",
				"signature": "",
				"replyList": []
			},
			{
				"id": "2000060227",
				"secret": 0,
				"pasterid": "",
				"bmp": "885195800202e101",
				"pubtime": "2014-06-09 17:38:27",
				"modifytime": 0,
				"effect": 4194336,
				"type": 0,
				"uin": 1991789548,
				"nickname": "蛹子小姐",
				"capacity": 5902,
				"htmlContent": "听说你养了只小狗狗。。",
				"ubbContent": "听说你养了只小狗狗。。",
				"signature": "",
				"replyList": [
					{
						"content": " 一秒钟变小狗　－　－",
						"uin": 1084677348,
						"time": 1402390031,
						"nick": "时不知鲑"
					}
				]
			},
			{
				"id": "2000060226",
				"secret": 0,
				"pasterid": "",
				"bmp": "885195800202e101",
				"pubtime": "2014-06-04 23:57:48",
				"modifytime": 0,
				"effect": 4194304,
				"type": 0,
				"uin": 1991789548,
				"nickname": "蛹子小姐",
				"capacity": 5941,
				"htmlContent": "然后把盒子留下来排排站。",
				"ubbContent": "然后把盒子留下来排排站。",
				"signature": "",
				"replyList": []
			},
			{
				"id": "2000060225",
				"secret": 0,
				"pasterid": "",
				"bmp": "885195800202e101",
				"pubtime": "2014-06-04 23:56:48",
				"modifytime": 0,
				"effect": 4194304,
				"type": 0,
				"uin": 1991789548,
				"nickname": "蛹子小姐",
				"capacity": 5923,
				"htmlContent": "每天早上都有一盒牛奶，上面写一句温暖的话。",
				"ubbContent": "每天早上都有一盒牛奶，上面写一句温暖的话。",
				"signature": "",
				"replyList": []
			},
			{
				"id": "2000060224",
				"secret": 0,
				"pasterid": "",
				"bmp": "885195800202e101",
				"pubtime": "2014-06-04 23:55:30",
				"modifytime": 0,
				"effect": 4194304,
				"type": 0,
				"uin": 1991789548,
				"nickname": "蛹子小姐",
				"capacity": 5959,
				"htmlContent": "哎。。",
				"ubbContent": "哎。。",
				"signature": "",
				"replyList": []
			},
			{
				"id": "2000060223",
				"secret": 0,
				"pasterid": "",
				"bmp": "885195800202e101",
				"pubtime": "2014-06-04 23:52:51",
				"modifytime": 0,
				"effect": 4194304,
				"type": 0,
				"uin": 1991789548,
				"nickname": "蛹子小姐",
				"capacity": 5929,
				"htmlContent": "越怕什么越抗拒什么，就越遇上了什么。",
				"ubbContent": "越怕什么越抗拒什么，就越遇上了什么。",
				"signature": "",
				"replyList": []
			},
			{
				"id": "2000060222",
				"secret": 0,
				"pasterid": "",
				"bmp": "885195800202e101",
				"pubtime": "2014-06-04 23:51:38",
				"modifytime": 0,
				"effect": 4194304,
				"type": 0,
				"uin": 1991789548,
				"nickname": "蛹子小姐",
				"capacity": 5941,
				"htmlContent": "有些话我不能跟任何人说。",
				"ubbContent": "有些话我不能跟任何人说。",
				"signature": "",
				"replyList": []
			},
			{
				"id": "2000060221",
				"secret": 0,
				"pasterid": "",
				"bmp": "885195800202e101",
				"pubtime": "2014-06-04 23:50:55",
				"modifytime": 0,
				"effect": 4194304,
				"type": 0,
				"uin": 1991789548,
				"nickname": "蛹子小姐",
				"capacity": 5939,
				"htmlContent": "想摆脱摆脱不了了的是什么。",
				"ubbContent": "想摆脱摆脱不了了的是什么。",
				"signature": "",
				"replyList": []
			},
			{
				"id": "2000060220",
				"secret": 0,
				"pasterid": "",
				"bmp": "885195800202e101",
				"pubtime": "2014-06-04 23:49:23",
				"modifytime": 0,
				"effect": 4194304,
				"type": 0,
				"uin": 1991789548,
				"nickname": "蛹子小姐",
				"capacity": 5887,
				"htmlContent": "我以为有些话你从来没对我讲过，后来才发现原来曾经有那么一阵你天天都有讲给我听。",
				"ubbContent": "我以为有些话你从来没对我讲过，后来才发现原来曾经有那么一阵你天天都有讲给我听。",
				"signature": "",
				"replyList": []
			}
		]
	}
}