{
  "code": 0,
  "subcode": 0,
  "message": "",
  "default": 0,
  "data": {
    "total": 1814,
    "auditNum": 0,
    "auditON": true,
    "authorInfo": { "msg": "", "htmlMsg": "", "sign": "" },
    "commentList": [
      {
        "id": "2000060027",
        "secret": 0,
        "pasterid": "",
        "bmp": "885195800202e101",
        "pubtime": "2013-12-06 13:29:25",
        "modifytime": 0,
        "effect": 4195328,
        "type": 0,
        "uin": 1991789548,
        "nickname": "蛹子小姐",
        "capacity": 5952,
        "htmlContent": "\u003Cimg src=\u0022/qzone/em/e152.gif\u0022  />\u003Cwbr  />",
        "ubbContent": "[em]e152[/em]",
        "signature": "",
        "replyList": []
      },
      {
        "id": "2000060026",
        "secret": 0,
        "pasterid": "",
        "bmp": "885195800202e101",
        "pubtime": "2013-12-06 09:13:59",
        "modifytime": 0,
        "effect": 4195328,
        "type": 0,
        "uin": 1991789548,
        "nickname": "蛹子小姐",
        "capacity": 5932,
        "htmlContent": "不过，老公真的最帅了\u003Cimg src=\u0022/qzone/em/e176.gif\u0022  />\u003Cwbr  />",
        "ubbContent": "不过，老公真的最帅了[em]e176[/em]",
        "signature": "",
        "replyList": []
      },
      {
        "id": "2000060025",
        "secret": 0,
        "pasterid": "",
        "bmp": "885195800202e101",
        "pubtime": "2013-12-06 09:07:53",
        "modifytime": 0,
        "effect": 4195328,
        "type": 0,
        "uin": 1991789548,
        "nickname": "蛹子小姐",
        "capacity": 5928,
        "htmlContent": "。。。我就知道你会羞涩的\u003Cimg src=\u0022/qzone/em/e144.gif\u0022  />\u003Cwbr  />",
        "ubbContent": "。。。我就知道你会羞涩的[em]e144[/em]",
        "signature": "",
        "replyList": []
      },
      {
        "id": "2000060024",
        "secret": 0,
        "pasterid": "",
        "bmp": "885195800202e101",
        "pubtime": "2013-12-06 09:07:20",
        "modifytime": 0,
        "effect": 4195328,
        "type": 0,
        "uin": 1991789548,
        "nickname": "蛹子小姐",
        "capacity": 5934,
        "htmlContent": "最帅了，林场最帅了\u003Cimg src=\u0022/qzone/em/e152.gif\u0022  />\u003Cwbr  />",
        "ubbContent": "最帅了，林场最帅了[em]e152[/em]",
        "signature": "",
        "replyList": []
      },
      {
        "id": "2000060023",
        "secret": 0,
        "pasterid": "",
        "bmp": "885195800202e101",
        "pubtime": "2013-12-06 09:06:52",
        "modifytime": 0,
        "effect": 4195328,
        "type": 0,
        "uin": 1991789548,
        "nickname": "蛹子小姐",
        "capacity": 5949,
        "htmlContent": "我老公最帅了！！",
        "ubbContent": "我老公最帅了！！",
        "signature": "",
        "replyList": []
      },
      {
        "id": "2000060022",
        "secret": 0,
        "pasterid": "",
        "bmp": "885195800202e101",
        "pubtime": "2013-12-06 09:06:38",
        "modifytime": 0,
        "effect": 4195328,
        "type": 0,
        "uin": 1991789548,
        "nickname": "蛹子小姐",
        "capacity": 5940,
        "htmlContent": "我老公最帅了\u003Cimg src=\u0022/qzone/em/e165.gif\u0022  />\u003Cwbr  />",
        "ubbContent": "我老公最帅了[em]e165[/em]",
        "signature": "",
        "replyList": []
      },
      {
        "id": "2000060021",
        "secret": 0,
        "pasterid": "",
        "bmp": "885195800202e101",
        "pubtime": "2013-12-06 09:05:35",
        "modifytime": 0,
        "effect": 4195328,
        "type": 0,
        "uin": 1991789548,
        "nickname": "蛹子小姐",
        "capacity": 5940,
        "htmlContent": "我老公最帅了\u003Cimg src=\u0022/qzone/em/e166.gif\u0022  />\u003Cwbr  />",
        "ubbContent": "我老公最帅了[em]e166[/em]",
        "signature": "",
        "replyList": []
      },
      {
        "id": "2000060020",
        "secret": 0,
        "pasterid": "",
        "bmp": "885195800202e101",
        "pubtime": "2013-12-06 09:05:30",
        "modifytime": 0,
        "effect": 4195328,
        "type": 0,
        "uin": 1991789548,
        "nickname": "蛹子小姐",
        "capacity": 5940,
        "htmlContent": "我老公最帅了\u003Cimg src=\u0022/qzone/em/e121.gif\u0022  />\u003Cwbr  />",
        "ubbContent": "我老公最帅了[em]e121[/em]",
        "signature": "",
        "replyList": []
      },
      {
        "id": "2000060019",
        "secret": 0,
        "pasterid": "",
        "bmp": "885195800202e101",
        "pubtime": "2013-12-06 09:03:46",
        "modifytime": 0,
        "effect": 4195328,
        "type": 0,
        "uin": 1991789548,
        "nickname": "蛹子小姐",
        "capacity": 5940,
        "htmlContent": "我老公最帅了\u003Cimg src=\u0022/qzone/em/e163.gif\u0022  />\u003Cwbr  />",
        "ubbContent": "我老公最帅了[em]e163[/em]",
        "signature": "",
        "replyList": []
      },
      {
        "id": "2000060018",
        "secret": 0,
        "pasterid": "",
        "bmp": "885195800202e101",
        "pubtime": "2013-12-06 09:02:49",
        "modifytime": 0,
        "effect": 4195328,
        "type": 0,
        "uin": 1991789548,
        "nickname": "蛹子小姐",
        "capacity": 5924,
        "htmlContent": "送你的时候好开心\u003Cimg src=\u0022/qzone/em/e120.gif\u0022  />\u003Cwbr  />我老公最帅了",
        "ubbContent": "送你的时候好开心[em]e120[/em]我老公最帅了",
        "signature": "",
        "replyList": []
      }
    ]
  }
}
